savic/SAVIC.py
savic/SAVIC_C_C.py
savic/SAVIC_C_CA.py
savic/SAVIC_C_CB.py
savic/SAVIC_C_CBA.py
savic/SAVIC_Core.py
savic/SAVIC_CoreAlpha.py
savic/SAVIC_CoreBeam.py
savic/SAVIC_CoreBeamAlpha.py
savic/SAVIC_Input_Sort.py
savic/SAVIC_P_C.py
savic/SAVIC_P_CA.py
savic/SAVIC_P_CB.py
savic/SAVIC_P_CBA.py
savic/SAVIC_Q_C.py
savic/SAVIC_Q_CA.py
savic/SAVIC_Q_CB.py
savic/SAVIC_Q_CBA.py
savic/__init__.py
savic/tutorial.py
savic/Output/ML/models/GMM_C/00_dummy.txt
savic/Output/ML/models/GMM_CA/00_dummy.txt
savic/Output/ML/models/GMM_CB/00_dummy.txt
savic/Output/ML/models/GMM_CBA/00_dummy.txt
savic/tutorial/00_dummy.txt
savic-1.2.6.dist-info/METADATA
savic-1.2.6.dist-info/WHEEL
savic-1.2.6.dist-info/licenses/LICENSE
savic-1.2.6.dist-info/RECORD
