Metadata-Version: 2.4
Name: savic
Version: 1.2.6
Summary: SAVIC package
Project-URL: Homepage, https://pypi.org/project/savic/
Project-URL: History, https://test.pypi.org/project/savic-test/
Project-URL: Source, https://github.com/MihailoMartinovic/SAVIC
Author-email: Mihailo Martinovic <mmartinovic@arizona.edu>
License-File: LICENSE
Classifier: License :: OSI Approved :: MIT License
Classifier: Operating System :: OS Independent
Classifier: Programming Language :: Python :: 3
Requires-Python: >=3.7
Requires-Dist: numpy>=1.24.3
Requires-Dist: pandas>=1.4.4
Requires-Dist: scikit-learn>=1.2.0
Requires-Dist: tables>=3.8.0
Requires-Dist: urllib3>=1.26.16
Requires-Dist: wget>=3.2
Requires-Dist: xgboost>=1.7.2
